testbench2robotframework/__init__.py
testbench2robotframework/__main__.py
testbench2robotframework/config.py
testbench2robotframework/json_reader.py
testbench2robotframework/json_writer.py
testbench2robotframework/log.py
testbench2robotframework/model.py
testbench2robotframework/result_writer.py
testbench2robotframework/robotframework2testbench.py
testbench2robotframework/testbench2rf.py
testbench2robotframework/testbench2robotframework.py
testbench2robotframework/testsuite_write.py
testbench2robotframework/utils.py
testbench2robotframework-0.7.0.dist-info/LICENSE
testbench2robotframework-0.7.0.dist-info/METADATA
testbench2robotframework-0.7.0.dist-info/WHEEL
testbench2robotframework-0.7.0.dist-info/entry_points.txt
testbench2robotframework-0.7.0.dist-info/top_level.txt
testbench2robotframework-0.7.0.dist-info/RECORD
