Metadata-Version: 2.1
Name: testbench2robotframework
Version: 0.7.0
Summary: Robot Framework Code Generator from Keyword-Driven Tests in imbus TestBench 3.0 and newer
Home-page: https://github.com/imbus/testbench2robotframework
Author: imbus AG
Author-email: support@imbus.de
License: Apache 2.0 License
Platform: any
Requires-Python: >=3.8
Requires-Dist: robotframework (>=5.0)
Provides-Extra: dev
Requires-Dist: black ; extra == 'dev'
Requires-Dist: flake8 ; extra == 'dev'
Requires-Dist: pylint ; extra == 'dev'
Requires-Dist: mypy ; extra == 'dev'
Requires-Dist: pytest ; extra == 'dev'
Requires-Dist: pytest-cov ; extra == 'dev'
Requires-Dist: pytest-spec ; extra == 'dev'
Requires-Dist: check-manifest ; extra == 'dev'
Requires-Dist: twine ; extra == 'dev'
Requires-Dist: wheel ; extra == 'dev'
Requires-Dist: setuptools ; extra == 'dev'
Requires-Dist: ruff ; extra == 'dev'
Requires-Dist: pip-tools ; extra == 'dev'
